hpln/__init__.py
hpln/helpers.py
hpln/hpln.py
hpln/default_abreviations/en.txt
hpln-0.8.dist-info/entry_points.txt
hpln-0.8.dist-info/LICENSE
hpln-0.8.dist-info/WHEEL
hpln-0.8.dist-info/METADATA
hpln-0.8.dist-info/RECORD
