Metadata-Version: 2.1
Name: hpln
Version: 0.8
Summary: Natural Language Processor
Author-email: Henrique Parola <pg50415@alunos.uminho.pt>
Classifier: License :: OSI Approved :: MIT License
Project-URL: Home, https://github.com/LittleLevi05/spln-2223/tree/main/TPC5
